setup.py
uiautomatorplug/__init__.py
uiautomatorplug/android.py
uiautomatorplug/comparison.py
uiautomatorplug.egg-info/PKG-INFO
uiautomatorplug.egg-info/SOURCES.txt
uiautomatorplug.egg-info/dependency_links.txt
uiautomatorplug.egg-info/requires.txt
uiautomatorplug.egg-info/top_level.txt