Metadata-Version: 1.1
Name: uiautomatorplug
Version: 1.1.1
Summary: enhancement for the python wrapperof android uiautomator. provides image comparision method
Home-page: UNKNOWN
Author: bao hongbin
Author-email: hongbin.bao@gmail.com
License: MIT
Platform: any
Classifier: Development Status :: 2 - Pre-Alpha
Classifier: Environment :: Console
Classifier: Intended Audience :: Developers
Classifier: Operating System :: POSIX :: Linux
Classifier: Programming Language :: Python
Classifier: Topic :: Software Development :: Libraries
Classifier: Topic :: Software Development :: Testing
